setup.cfg
setup.py
Buro.egg-info/PKG-INFO
Buro.egg-info/SOURCES.txt
Buro.egg-info/dependency_links.txt
Buro.egg-info/requires.txt
Buro.egg-info/top_level.txt
buro/__init__.py
buro/core.py
buro/errors.py
buro/responses.py
buro/settings.py
buro/shared.py
buro/urls.py
buro/utils.py