Metadata-Version: 1.0
Name: Buro
Version: 0.1.27
Summary: A very simple Python-powered open-source web framework inspired by Flask, but following different design decisions
Home-page: http://buro.sourceinhabitants.com/
Author: Thomas Pelletier
Author-email: thomas@pelletier.im
License: BSD
Platform: any
Classifier: Development Status :: 4 - Beta
Classifier: Environment :: Web Environment
Classifier: Intended Audience :: Developers
Classifier: License :: OSI Approved :: BSD License
Classifier: Operating System :: OS Independent
Classifier: Programming Language :: Python
Classifier: Topic :: Internet :: WWW/HTTP :: Dynamic Content
Classifier: Topic :: Software Development :: Libraries :: Python Modules
